{"httpProtocol":"HTTP/1.1","clientAcceptEncoding":"gzip, deflate, br","requestPriority":"","edgeRequestKeepAliveStatus":1,"requestHeaderNames":{},"clientTcpRtt":7,"clientQuicRtt":0,"colo":"ZRH","asn":15796,"asOrganization":"Salt Mobile SA","country":"CH","isEUCountry":false,"city":"Zürich","continent":"EU","region":"Zurich","regionCode":"ZH","timezone":"Europe/Zurich","longitude":"8.55","latitude":"47.36667","postalCode":"8000","tlsVersion":"TLSv1.3","tlsCipher":"AEAD-AES256-GCM-SHA384","tlsClientRandom":"w8ucMFFlBMzeHAUT7yRHqt+fkzFdCIoBHr6y68jdhiM=","tlsClientCiphersSha1":"kXrN3VEKDdzz2cPKTQaKzpxVTxQ=","tlsClientExtensionsSha1":"1eY97BUYYO8vDaTfHQywB1pcNdM=","tlsClientExtensionsSha1Le":"u4wtEMFQBY18l3BzHAvORm+KGRw=","tlsExportedAuthenticator":{"clientHandshake":"a96595cfc9b85d26019fc9c41c48a60368529dacf201e9ec1f8b55380693e89ef841be536e387f541f62e4556964d3ab","serverHandshake":"dcc3cc673a0a823a9376f05cb27df1b3dc61c4ed0522042d36536ea6f822972d9bc83007cd3dad3342124182469a9052","clientFinished":"54667ca209c3d6a56147b5eae4423e75e7ae5cbd6bc987b565536b1ca9e9385b066f5f6f01bb76dfd0c3e2db3200bb02","serverFinished":"2de75eb6563fccc84e38495f2b10faa81acd247b72fc59ddc91b0a0a6d4dc54346aed0778af53f6dbea14a582aed4363"},"tlsClientHelloLength":"1603","tlsClientAuth":{"certPresented":"0","certVerified":"NONE","certRevoked":"0","certIssuerDN":"","certSubjectDN":"","certIssuerDNRFC2253":"","certSubjectDNRFC2253":"","certIssuerDNLegacy":"","certSubjectDNLegacy":"","certSerial":"","certIssuerSerial":"","certSKI":"","certIssuerSKI":"","certFingerprintSHA1":"","certFingerprintSHA256":"","certNotBefore":"","certNotAfter":"","certRFC9440":"","certRFC9440TooLarge":false,"certChainRFC9440":"","certChainRFC9440TooLarge":false},"verifiedBotCategory":"","edgeL4":{"deliveryRate":650104},"botManagement":{"corporateProxy":false,"verifiedBot":false,"jsDetection":{"passed":false},"staticResource":false,"detectionIds":{},"score":99}}